Workbook

Sheet Resumo
A1: Votações nominais de Flávio Bolsonaro no plenário do Senado (57ª legislatura, fev/2023 a out/2026)
A2: Fonte: Senado Federal, Portal de Dados Abertos (legis.senado.leg.br/dadosabertos), consulta em 23/10/2026. Inclui só votações nominais de plenário; votações simbólicas e de comissões não estão aqui.
A4: Registro | B4: 2023 | C4: 2024 | D4: 2025 | E4: 2026 | F4: Total
A5: Sim | B5: =COUNTIFS(Votações!$F$2:$F$427,$A5,Votações!$B$2:$B$427,"2023") -> 30 | C5: =COUNTIFS(Votações!$F$2:$F$427,$A5,Votações!$B$2:$B$427,"2024") -> 43 | D5: =COUNTIFS(Votações!$F$2:$F$427,$A5,Votações!$B$2:$B$427,"2025") -> 28 | E5: =COUNTIFS(Votações!$F$2:$F$427,$A5,Votações!$B$2:$B$427,"2026") -> 8 | F5: =SUM(B5:E5) -> 109
A6: Não | B6: =COUNTIFS(Votações!$F$2:$F$427,$A6,Votações!$B$2:$B$427,"2023") -> 14 | C6: =COUNTIFS(Votações!$F$2:$F$427,$A6,Votações!$B$2:$B$427,"2024") -> 13 | D6: =COUNTIFS(Votações!$F$2:$F$427,$A6,Votações!$B$2:$B$427,"2025") -> 10 | E6: =COUNTIFS(Votações!$F$2:$F$427,$A6,Votações!$B$2:$B$427,"2026") -> 1 | F6: =SUM(B6:E6) -> 38
A7: Abstenção | B7: =COUNTIFS(Votações!$F$2:$F$427,$A7,Votações!$B$2:$B$427,"2023") -> 0 | C7: =COUNTIFS(Votações!$F$2:$F$427,$A7,Votações!$B$2:$B$427,"2024") -> 0 | D7: =COUNTIFS(Votações!$F$2:$F$427,$A7,Votações!$B$2:$B$427,"2025") -> 1 | E7: =COUNTIFS(Votações!$F$2:$F$427,$A7,Votações!$B$2:$B$427,"2026") -> 0 | F7: =SUM(B7:E7) -> 1
A8: Votou | B8: =COUNTIFS(Votações!$F$2:$F$427,$A8,Votações!$B$2:$B$427,"2023") -> 67 | C8: =COUNTIFS(Votações!$F$2:$F$427,$A8,Votações!$B$2:$B$427,"2024") -> 31 | D8: =COUNTIFS(Votações!$F$2:$F$427,$A8,Votações!$B$2:$B$427,"2025") -> 60 | E8: =COUNTIFS(Votações!$F$2:$F$427,$A8,Votações!$B$2:$B$427,"2026") -> 23 | F8: =SUM(B8:E8) -> 181
A9: Presente – Não registrou voto | B9: =COUNTIFS(Votações!$F$2:$F$427,$A9,Votações!$B$2:$B$427,"2023") -> 26 | C9: =COUNTIFS(Votações!$F$2:$F$427,$A9,Votações!$B$2:$B$427,"2024") -> 8 | D9: =COUNTIFS(Votações!$F$2:$F$427,$A9,Votações!$B$2:$B$427,"2025") -> 17 | E9: =COUNTIFS(Votações!$F$2:$F$427,$A9,Votações!$B$2:$B$427,"2026") -> 16 | F9: =SUM(B9:E9) -> 67
A10: Não Compareceu | B10: =COUNTIFS(Votações!$F$2:$F$427,$A10,Votações!$B$2:$B$427,"2023") -> 0 | C10: =COUNTIFS(Votações!$F$2:$F$427,$A10,Votações!$B$2:$B$427,"2024") -> 0 | D10: =COUNTIFS(Votações!$F$2:$F$427,$A10,Votações!$B$2:$B$427,"2025") -> 2 | E10: =COUNTIFS(Votações!$F$2:$F$427,$A10,Votações!$B$2:$B$427,"2026") -> 10 | F10: =SUM(B10:E10) -> 12
A11: Licença Particular | B11: =COUNTIFS(Votações!$F$2:$F$427,$A11,Votações!$B$2:$B$427,"2023") -> 0 | C11: =COUNTIFS(Votações!$F$2:$F$427,$A11,Votações!$B$2:$B$427,"2024") -> 0 | D11: =COUNTIFS(Votações!$F$2:$F$427,$A11,Votações!$B$2:$B$427,"2025") -> 8 | E11: =COUNTIFS(Votações!$F$2:$F$427,$A11,Votações!$B$2:$B$427,"2026") -> 1 | F11: =SUM(B11:E11) -> 9
A12: Atividade parlamentar | B12: =COUNTIFS(Votações!$F$2:$F$427,$A12,Votações!$B$2:$B$427,"2023") -> 4 | C12: =COUNTIFS(Votações!$F$2:$F$427,$A12,Votações!$B$2:$B$427,"2024") -> 0 | D12: =COUNTIFS(Votações!$F$2:$F$427,$A12,Votações!$B$2:$B$427,"2025") -> 2 | E12: =COUNTIFS(Votações!$F$2:$F$427,$A12,Votações!$B$2:$B$427,"2026") -> 3 | F12: =SUM(B12:E12) -> 9
A13: Total de votações nominais | B13: =SUM(B5:B12) -> 141 | C13: =SUM(C5:C12) -> 95 | D13: =SUM(D5:D12) -> 128 | E13: =SUM(E5:E12) -> 62 | F13: =SUM(F5:F12) -> 426
A14: Presença sem registro de voto, ausência ou licença (% do total) | B14: =IF(B13=0,0,SUM(B9:B12)/B13) -> 0.21276596 | C14: =IF(C13=0,0,SUM(C9:C12)/C13) -> 0.084210526 | D14: =IF(D13=0,0,SUM(D9:D12)/D13) -> 0.2265625 | E14: =IF(E13=0,0,SUM(E9:E12)/E13) -> 0.48387097 | F14: =IF(F13=0,0,SUM(F9:F12)/F13) -> 0.22769953
A16: Como ler os registros
A17: Sim / Não / Abstenção: voto declarado em matérias legislativas (PEC, projetos, MPs, requerimentos, destaques).
A18: Votou: votação secreta, quase sempre de indicação de autoridade (embaixadores, agências, tribunais, CNJ, CNMP). O conteúdo do voto não é público.
A19: Presente – Não registrou voto: estava na sessão mas não votou naquela votação.
A20: Não Compareceu: ausente sem justificativa registrada.
A21: Licença Particular / Atividade parlamentar: ausência justificada (licença pessoal ou missão oficial).
A22: Resultado: Aprovado ou Rejeitado refere-se ao item votado. Em destaques e emendas, "Rejeitado" significa que a mudança caiu e o texto original foi mantido.

Sheet Votações
A1: Data | B1: Ano | C1: Matéria | D1: Tipo | E1: O que foi votado | F1: Voto de Flávio Bolsonaro | G1: Resultado | H1: Código da votação
A2: 44965 | B2: 2023 | C2: PDL 2/2023 | D2: Outros | E2: Projeto de Decreto Legislativo nº 2/2023 | F2: Votou | G2: Aprovado | H2: 6674
A3: 45013 | B3: 2023 | C3: PLP 189/2019 | D3: Lei complementar | E3: PLP 189/2019, nos termos do parecer | F3: Sim | G3: Aprovado | H3: 6675
A4: 45035 | B4: 2023 | C4: PRS 46/2023 | D4: Outros | E4: Projeto de Resolução nº 46/2023 | F4: Sim | G4: Aprovado | H4: 6676
A5: 45055 | B5: 2023 | C5: PL 1825/2022 (Substitutivo-CD) | D5: Projeto de lei | E5: Expressões do Substitutivo da CD ao PLS 68/2017, destacadas | F5: Não | G5: Aprovado | H5: 6677
A6: 45055 | B6: 2023 | C6: PLS 332/2018 | D6: Projeto de lei | E6: PLS 332/2018 - Complementar | F6: Sim | G6: Aprovado | H6: 6678
A7: 45056 | B7: 2023 | C7: PLP 245/2019 | D7: Lei complementar | E7: Emenda nº 48 (Substitutivo) ao PLP 245/2019 | F7: Sim | G7: Aprovado | H7: 6679
A8: 45062 | B8: 2023 | C8: PEC 162/2019 | D8: PEC | E8: PEC 162/2019 (1º turno) | F8: Sim | G8: Aprovado | H8: 6680
A9: 45062 | B9: 2023 | C9: PEC 162/2019 | D9: PEC | E9: PEC 162/2019 (2º turno) | F9: Sim | G9: Aprovado | H9: 6681
A10: 45063 | B10: 2023 | C10: MSF 5/2023 | D10: Autoridade (voto secreto) | E10: Indicação: Paulino Franco de Carvalho Neto (Egito e Eritreia) | F10: Votou | G10: Aprovado | H10: 6682
A11: 45063 | B11: 2023 | C11: MSF 6/2023 | D11: Autoridade (voto secreto) | E11: Indicação: Ricardo Neiva Tavares (França e Mônaco) | F11: Votou | G11: Aprovado | H11: 6683
A12: 45063 | B12: 2023 | C12: MSF 23/2023 | D12: Autoridade (voto secreto) | E12: Indicação: Erick Moura de Medeiros (DNIT) | F12: Presente – Não registrou voto | G12: Aprovado | H12: 6684
A13: 45063 | B13: 2023 | C13: MSF 9/2023 | D13: Autoridade (voto secreto) | E13: Indicação: Maria Luiza Ribeiro Viotti (EUA) | F13: Presente – Não registrou voto | G13: Aprovado | H13: 6685
... A427: 46310 | B427: 2026 | C427: PLP 186/2026 | D427: Lei complementar | E427: PLP 186/2026, nos termos do parecer | F427: Sim | G427: Aprovado | H427: 7108

Sheet Matérias e sinais
A1: Data | B1: Matéria | C1: Tipo de votação | D1: O que estava em votação | E1: Voto de Flávio Bolsonaro | F1: Placar (Sim a Não) | G1: Resultado | H1: Orientação do governo | I1: Orientação do PL | J1: Sinais automáticos | K1: Código da votação
A2: 45013 | B2: PLP 189/2019 | C2: Texto principal | D2: Inclui o município de Uruana de Minas na RIDE do Distrito Federal | E2: Sim | F2: 59 a 0 | G2: Aprovado | H2: Não orientou | I2: Não orientou | K2: 6675
A3: 45035 | B3: PRS 46/2023 | C3: Texto principal | D3: Autoriza Recife a contratar crédito externo de até US$ 260 milhões | E3: Sim | F3: 63 a 0 | G3: Aprovado | H3: Sim | I3: Sim | J3: voto com placar folgado | K3: 6676
A4: 45055 | B4: PL 1825/2022 (Substitutivo-CD) | C4: Destaque ou emenda | D4: Mantém na Lei Geral do Esporte as expressões que combatem racismo, xenofobia, homofobia e sexismo | E4: Não | F4: 43 a 23 | G4: Aprovado | H4: Sim | I4: Não | J4: contra o governo | K4: 6677
A5: 45055 | B5: PLS 332/2018 | C5: Texto principal | D5: Veda ICMS na transferência de mercadoria entre estabelecimentos do mesmo contribuinte | E5: Sim | F5: 62 a 0 | G5: Aprovado | H5: Sim | I5: Não orientou | J5: voto com placar folgado | K5: 6678
A6: 45056 | B6: PLP 245/2019 | C6: Texto principal | D6: Regulamenta a aposentadoria especial no Regime Geral de Previdência | E6: Sim | F6: 66 a 0 | G6: Aprovado | H6: Sim | I6: Liberou | J6: voto com placar folgado | K6: 6679
A7: 45062 | B7: PEC 162/2019 | C7: Texto principal | D7: Permite permuta entre juízes de tribunais diferentes | E7: Sim | F7: 67 a 0 | G7: Aprovado | H7: Sim | I7: Sim | J7: PEC: folga sobre os 49 votos = 18; voto com placar folgado | K7: 6680
A8: 45062 | B8: PEC 162/2019 | C8: Texto principal | D8: Permite permuta entre juízes de tribunais diferentes | E8: Sim | F8: 67 a 0 | G8: Aprovado | H8: Sim | I8: Sim | J8: PEC: folga sobre os 49 votos = 18; voto com placar folgado | K8: 6681
A9: 45077 | B9: MPV 1154/2023 | C9: Texto principal | D9: Organização dos ministérios do governo Lula (MPV 1.154/2023) | E9: Não | F9: 51 a 19 | G9: Aprovado | H9: Sim | I9: Não | J9: contra o governo | K9: 6704
A10: 45083 | B10: PEC 43/2022 | C10: Texto principal | D10: Prazo adicional para permissões lotéricas | E10: Sim | F10: 65 a 1 | G10: Aprovado | H10: Não orientou | I10: Sim | J10: PEC: folga sobre os 49 votos = 16; voto com placar folgado | K10: 6705
A11: 45083 | B11: PEC 43/2022 | C11: Texto principal | D11: Prazo adicional para permissões lotéricas | E11: Sim | F11: 62 a 0 | G11: Aprovado | H11: Não orientou | I11: Sim | J11: PEC: folga sobre os 49 votos = 13; voto com placar folgado | K11: 6706
A12: 45091 | B12: PLP 139/2022 | C12: Texto principal | D12: Mantém coeficientes do FPM de municípios que perderam população no Censo | E12: Presente – Não registrou voto | F12: 67 a 0 | G12: Aprovado | H12: Liberou | I12: Sim | J12: presente sem votar (votou outros itens no dia) | K12: 6708
A13: 45097 | B13: MPV 1165/2023 | C13: Destaque ou emenda | D13: Emenda à MPV 1.165/2023 (Mais Médicos) | E13: Sim | F13: 29 a 47 | G13: Rejeitado | H13: Não | I13: Sim | J13: contra o governo | K13: 6709
A14: 45098 | B14: PLP 93/2023 | C14: Texto principal | D14: Regime fiscal sustentável (arcabouço fiscal) | E14: Não | F14: 57 a 17 | G14: Aprovado | H14: Sim | I14: Não | J14: contra o governo | K14: 6714
... A16: 45098 | B16: PLP 93/2023 | C16: Destaque ou emenda | D16: Emenda ao arcabouço fiscal | E16: Sim | F16: 21 a 48 | G16: Rejeitado | H16: Não | I16: Sim | J16: contra o governo | K16: 6716
A17: 45098 | B17: PLP 93/2023 | C17: Destaque ou emenda | D17: Emenda ao arcabouço fiscal | E17: Não | F17: 5 a 59 | G17: Rejeitado | H17: Não | I17: Não | K17: 6717
A18: 45112 | B18: PLP 41/2019 | C18: Texto principal | D18: Critérios e metas para avaliar benefícios fiscais | E18: Sim | F18: 65 a 0 | G18: Aprovado | H18: Sim | I18: Sim | J18: voto com placar folgado | K18: 6730
A19: 45112 | B19: PLP 178/2021 | C19: Texto principal | D19: Estatuto de simplificação de obrigações tributárias acessórias | E19: Sim | F19: 59 a 0 | G19: Aprovado | H19: Sim | I19: Sim | K19: 6731
A20: 45167 | B20: PLP 257/2019 | C20: Texto principal | D20: Resposta financeira da União a calamidades públicas | E20: Sim | F20: 61 a 0 | G20: Aprovado | H20: Sim | I20: Sim | J20: voto com placar folgado | K20: 6744
A21: 45168 | B21: PL 2384/2023 | C21: Texto principal | D21: Voto de qualidade no Carf e contencioso tributário | E21: Não | F21: 34 a 27 | G21: Aprovado | H21: Sim | I21: Não | J21: contra o governo | K21: 6745
A22: 45181 | B22: PEC 7/2018 | C22: Texto principal | D22: Quadro em extinção de servidores dos ex-territórios | E22: Sim | F22: 70 a 0 | G22: Aprovado | H22: Sim | I22: Sim | J22: PEC: folga sobre os 49 votos = 21; voto com placar folgado | K22: 6746
A23: 45181 | B23: PEC 7/2018 | C23: Texto principal | D23: Quadro em extinção de servidores dos ex-territórios | E23: Sim | F23: 68 a 0 | G23: Aprovado | H23: Sim | I23: Sim | J23: PEC: folga sobre os 49 votos = 19; voto com placar folgado | K23: 6747
A24: 45196 | B24: REQ 31/2023 - CCJ | C24: Procedimento | D24: Urgência para o marco temporal das terras indígenas | E24: Atividade parlamentar | F24: 41 a 20 | G24: Aprovado | H24: Não | I24: Sim | J24: ausente | K24: 6755
A25: 45196 | B25: PL 2903/2023 | C25: Texto principal | D25: Marco temporal das terras indígenas | E25: Atividade parlamentar | F25: 43 a 21 | G25: Aprovado | H25: Não | I25: Sim | J25: ausente | K25: 6756
A26: 45196 | B26: PL 2903/2023 | C26: Destaque ou emenda | D26: Marco temporal, dispositivo destacado | E26: Atividade parlamentar | F26: 34 a 22 | G26: Aprovado | H26: Não | I26: Sim | J26: ausente | K26: 6757
A27: 45196 | B27: PL 2903/2023 | C27: Destaque ou emenda | D27: Marco temporal, dispositivo destacado | E27: Atividade parlamentar | F27: 34 a 22 | G27: Aprovado | H27: Não | I27: Sim | J27: ausente | K27: 6758
A28: 45203 | B28: PLP 136/2023 | C28: Texto principal | D28: Compensação da União aos estados pelas perdas de ICMS | E28: Sim | F28: 63 a 2 | G28: Aprovado | H28: Sim | I28: Liberou | J28: voto com placar folgado | K28: 6759
A29: 45209 | B29: PL 2721/2023 | C29: Texto principal | D29: Serviços postais dos órgãos públicos federais pelos Correios | E29: Não | F29: 41 a 23 | G29: Aprovado | H29: Sim | I29: Não | J29: contra o governo | K29: 6760
A30: 45223 | B30: PL 5384/2020 | C30: Procedimento | D30: Preferência para substitutivo ao PL 5.384/2020 | E30: Sim | F30: 24 a 46 | G30: Rejeitado | H30: Não | I30: Sim | J30: contra o governo | K30: 6761
A31: 45230 | B31: PL 2470/2022 | C31: Procedimento | D31: Adiamento da votação do PL 2.470/2022 | E31: Não | F31: 37 a 34 | G31: Aprovado | H31: Sim | I31: Não | J31: contra o governo | K31: 6768
... A39: 45244 | B39: PLP 205/2023 | C39: Texto principal | D39: Prorroga prazo de execução da Lei Paulo Gustavo | E39: Sim | F39: 74 a 0 | G39: Aprovado | H39: Sim | I39: Não orientou | J39: voto com placar folgado | K39: 6778
A40: 45251 | B40: RQS 1039/2023 | C40: Procedimento | D40: Calendário especial para PEC que limita decisões individuais no STF | E40: Sim | F40: 48 a 20 | G40: Aprovado | H40: Não orientou | I40: Sim | K40: 6779
A41: 45251 | B41: PEC 8/2021 | C41: Procedimento | D41: Calendário especial para PEC que limita decisões individuais no STF | E41: Sim | F41: 48 a 20 | G41: Aprovado | H41: Não orientou | I41: Sim | K41: 6780
A42: 45252 | B42: PEC 8/2021 | C42: Destaque ou emenda | D42: Limita pedidos de vista e decisões individuais nos tribunais, 1º turno | E42: Sim | F42: 52 a 18 | G42: Aprovado | H42: Não orientou | I42: Sim | K42: 6781
A43: 45252 | B43: PEC 8/2021 | C43: Texto principal | D43: Limita pedidos de vista e decisões individuais nos tribunais, 2º turno | E43: Sim | F43: 52 a 18 | G43: Aprovado | H43: Não orientou | I43: Sim | J43: PEC: folga sobre os 49 votos = 3 | K43: 6782
A44: 45259 | B44: PLP 243/2023 | C44: Texto principal | D44: Despesas com programa de permanência de estudantes no ensino médio (Pé-de-Meia) | E44: Sim | F44: 61 a 0 | G44: Aprovado | H44: Sim | I44: Sim | J44: voto com placar folgado | K44: 6783
A45: 45272 | B45: RQS 1103/2023 | C45: Procedimento | D45: Encerramento da discussão do projeto das apostas esportivas | E45: Não | F45: 45 a 14 | G45: Aprovado | H45: Não orientou | I45: Sim | J45: contra o PL | K45: 6796
A46: 45272 | B46: PL 3626/2023 | C46: Destaque ou emenda | D46: Emenda ao projeto das apostas esportivas | E46: Sim | F46: 37 a 27 | G46: Aprovado | H46: Não | I46: Sim | J46: contra o governo | K46: 6797
A47: 45272 | B47: PL 3626/2023 | C47: Destaque ou emenda | D47: Emenda ao projeto das apostas esportivas | E47: Sim | F47: 45 a 23 | G47: Aprovado | H47: Não | I47: Sim | J47: contra o governo | K47: 6798
A48: 45272 | B48: PL 3626/2023 | C48: Procedimento | D48: Encerramento da discussão do projeto das apostas esportivas | E48: Não | F48: 45 a 14 | G48: Aprovado | H48: Não orientou | I48: Sim | J48: contra o PL | K48: 6799
A49: 45272 | B49: PL 3626/2023 | C49: Destaque ou emenda | D49: Emenda ao projeto das apostas esportivas | E49: Sim | F49: 25 a 36 | G49: Rejeitado | H49: Não | I49: Liberou | J49: contra o governo | K49: 6800
A50: 45280 | B50: MPV 1185/2023 | C50: Texto principal | D50: Subvenções de ICMS e crédito fiscal (MPV 1.185/2023) | E50: Não | F50: 48 a 22 | G50: Aprovado | H50: Sim | I50: Não | J50: contra o governo | K50: 6816
A51: 45280 | B51: MPV 1185/2023 | C51: Destaque ou emenda | D51: Emenda à MPV das subvenções de ICMS | E51: Sim | F51: 31 a 41 | G51: Rejeitado | H51: Não | I51: Sim | J51: contra o governo | K51: 6817
A52: 45342 | B52: PL 2253/2022 | C52: Texto principal | D52: Fim da saída temporária de presos e exame criminológico para progressão | E52: Sim | F52: 62 a 2 | G52: Aprovado | H52: Liberou | I52: Sim | J52: voto com placar folgado | K52: 6818
A53: 45342 | B53: PL 2253/2022 | C53: Destaque ou emenda | D53: Emenda ao projeto da saída temporária | E53: Não | F53: 27 a 37 | G53: Rejeitado | H53: Liberou | I53: Não | K53: 6819
A54: 45356 | B54: PLP 137/2019 | C54: Texto principal | D54: Cédula de crédito microempresarial para micro e pequenas empresas | E54: Não | F54: 62 a 3 | G54: Aprovado | H54: Não orientou | I54: Liberou | K54: 6820
A55: 45364 | B55: PEC 72/2023 | C55: Texto principal | D55: Isenção de IPVA para veículos com mais de 20 anos, 1º turno | E55: Sim | F55: 66 a 4 | G55: Aprovado | H55: Sim | I55: Sim | J55: PEC: folga sobre os 49 votos = 17 | K55: 6821
A56: 45364 | B56: PEC 72/2023 | C56: Texto principal | D56: Isenção de IPVA para veículos com mais de 20 anos, 2º turno | E56: Sim | F56: 65 a 4 | G56: Aprovado | H56: Sim | I56: Sim | J56: PEC: folga sobre os 49 votos = 16 | K56: 6822
A57: 45392 | B57: PLP 252/2023 | C57: Texto principal | D57: Contrato de investimento conversível em capital social (startups) | E57: Sim | F57: 71 a 0 | G57: Aprovado | H57: Sim | I57: Sim | J57: voto com placar folgado | K57: 6823
A58: 45398 | B58: PEC 45/2023 | C58: Texto principal | D58: PEC que criminaliza porte de qualquer quantidade de droga, 1º turno | E58: Sim | F58: 53 a 9 | G58: Aprovado | H58: Não orientou | I58: Sim | J58: PEC: folga sobre os 49 votos = 4 | K58: 6824
A59: 45398 | B59: PEC 45/2023 | C59: Texto principal | D59: PEC que criminaliza porte de qualquer quantidade de droga, 2º turno | E59: Sim | F59: 52 a 9 | G59: Aprovado | H59: Não orientou | I59: Sim | J59: PEC: folga sobre os 49 votos = 3 | K59: 6825
A60: 45399 | B60: PLP 175/2023 | C60: Texto principal | D60: Prazo para estados e municípios executarem transposições de saldos | E60: Sim | F60: 57 a 0 | G60: Aprovado | H60: Sim | I60: Sim | K60: 6826
A61: 45420 | B61: PLP 233/2023 | C61: Texto principal | D61: Recria o seguro obrigatório para vítimas de acidentes de trânsito (SPVAT) | E61: Não | F61: 41 a 28 | G61: Aprovado | H61: Sim | I61: Não | J61: contra o governo | K61: 6827
A62: 45420 | B62: PLP 233/2023 | C62: Destaque ou emenda | D62: Dispositivo destacado do SPVAT | E62: Não | F62: 43 a 25 | G62: Aprovado | H62: Sim | I62: Não | J62: contra o governo | K62: 6828
A63: 45420 | B63: PLP 233/2023 | C63: Destaque ou emenda | D63: Emenda ao SPVAT | E63: Sim | F63: 25 a 39 | G63: Rejeitado | H63: Não | I63: Sim | J63: contra o governo | K63: 6829
A64: 45420 | B64: PLP 233/2023 | C64: Destaque ou emenda | D64: Emenda ao SPVAT | E64: Sim | F64: 27 a 33 | G64: Rejeitado | H64: Não | I64: Sim | J64: contra o governo | K64: 6830
A65: 45427 | B65: PLP 85/2024 | C65: Texto principal | D65: Adia dívida de estados atingidos por calamidade (Rio Grande do Sul) | E65: Sim | F65: 61 a 0 | G65: Aprovado | H65: Sim | I65: Sim | J65: voto com placar folgado | K65: 6831
A66: 45427 | B66: PLP 85/2024 | C66: Destaque ou emenda | D66: Emenda ao projeto da dívida dos estados em calamidade | E66: Sim | F66: 30 a 33 | G66: Rejeitado | H66: Não | I66: Sim | J66: contra o governo | K66: 6832
A67: 45434 | B67: PLP 150/2021 | C67: Texto principal | D67: Proteção à população LGBT+ encarcerada | E67: Sim | F67: 62 a 2 | G67: Aprovado | H67: Não orientou | I67: Liberou | J67: voto com placar folgado | K67: 6833
A68: 45434 | B68: RQS 369/2024 | C68: Procedimento | D68: Requerimento de Flávio Bolsonaro de preferência para substitutivo ao PL 1.958/2021 | E68: Sim | F68: 29 a 32 | G68: Rejeitado | H68: Não | I68: Sim | J68: contra o governo | K68: 6834
A69: 45434 | B69: PL 1958/2021 | C69: Procedimento | D69: Requerimento de Flávio Bolsonaro de preferência para substitutivo ao PL 1.958/2021 | E69: Sim | F69: 29 a 32 | G69: Rejeitado | H69: Não | I69: Sim | J69: contra o governo | K69: 6835
A70: 45448 | B70: PL 914/2024 | C70: Texto principal | D70: Programa Mobilidade Verde e Inovação (Mover) e conteúdo local | E70: Sim | F70: 67 a 0 | G70: Aprovado | H70: Sim | I70: Sim | J70: voto com placar folgado | K70: 6836
A71: 45461 | B71: PLC 29/2017 | C71: Destaque ou emenda | D71: Capítulo destacado do PLC 29/2017 | E71: Não | F71: 41 a 27 | G71: Aprovado | H71: Sim | I71: Não | J71: contra o governo | K71: 6837
A72: 45475 | B72: PLP 72/2024 | C72: Texto principal | D72: Gastos com hospitais universitários no mínimo constitucional da saúde | E72: Sim | F72: 60 a 0 | G72: Aprovado | H72: Sim | I72: Sim | J72: voto com placar folgado | K72: 6848
A73: 45476 | B73: PL 2308/2023 | C73: Destaque ou emenda | D73: Emenda ao PL 2.308/2023 | E73: Presente – Não registrou voto | F73: 8 a 50 | G73: Rejeitado | H73: Não | I73: Não | J73: presente sem votar (votou outros itens no dia) | K73: 6849
A74: 45476 | B74: PLP 262/2019 | C74: Texto principal | D74: Cooperativas nos fundos de desenvolvimento do Nordeste, Amazônia e Centro-Oeste | E74: Sim | F74: 50 a 0 | G74: Aprovado | H74: Sim | I74: Sim | K74: 6850
A75: 45517 | B75: SCD 6/2016 | C75: Destaque ou emenda | D75: Dispositivo destacado do substitutivo ao PLS 135/2010 | E75: Sim | F75: 17 a 48 | G75: Rejeitado | H75: Não orientou | I75: Sim | K75: 6862
A76: 45518 | B76: PLP 121/2024 | C76: Texto principal | D76: Programa de pagamento das dívidas dos estados (Propag) | E76: Sim | F76: 70 a 2 | G76: Aprovado | H76: Sim | I76: Sim | J76: voto com placar folgado | K76: 6863
A77: 45518 | B77: PEC 66/2023 | C77: Texto principal | D77: Parcelamento de dívidas previdenciárias dos municípios, 1º turno | E77: Sim | F77: 64 a 0 | G77: Aprovado | H77: Sim | I77: Sim | J77: PEC: folga sobre os 49 votos = 15; voto com placar folgado | K77: 6867
A78: 45518 | B78: PEC 66/2023 | C78: Texto principal | D78: Parcelamento de dívidas previdenciárias dos municípios, 2º turno | E78: Sim | F78: 63 a 0 | G78: Aprovado | H78: Sim | I78: Sim | J78: PEC: folga sobre os 49 votos = 14; voto com placar folgado | K78: 6868
A79: 45518 | B79: PEC 26/2022 | C79: Texto principal | D79: Eleição dos órgãos diretivos dos Tribunais de Justiça, 1º turno | E79: Sim | F79: 57 a 5 | G79: Aprovado | H79: Não orientou | I79: Sim | J79: PEC: folga sobre os 49 votos = 8 | K79: 6869
A80: 45518 | B80: PEC 26/2022 | C80: Texto principal | D80: Eleição dos órgãos diretivos dos Tribunais de Justiça, 2º turno | E80: Sim | F80: 57 a 3 | G80: Aprovado | H80: Não orientou | I80: Sim | J80: PEC: folga sobre os 49 votos = 8 | K80: 6870
A81: 45518 | B81: PEC 9/2023 | C81: Texto principal | D81: Recursos para candidaturas negras e refinanciamento de dívidas de partidos, 1º turno | E81: Sim | F81: 51 a 15 | G81: Aprovado | H81: Não orientou | I81: Sim | J81: PEC: folga sobre os 49 votos = 2 | K81: 6873
A82: 45518 | B82: PEC 9/2023 | C82: Texto principal | D82: Recursos para candidaturas negras e refinanciamento de dívidas de partidos, 2º turno | E82: Sim | F82: 54 a 16 | G82: Aprovado | H82: Não orientou | I82: Sim | J82: PEC: folga sobre os 49 votos = 5 | K82: 6874
A83: 45539 | B83: PL 528/2020 | C83: Destaque ou emenda | D83: Emenda ao PL 528/2020 | E83: Sim | F83: 44 a 25 | G83: Aprovado | H83: Não | I83: Sim | J83: contra o governo | K83: 6875
A84: 45608 | B84: PL 182/2024 | C84: Destaque ou emenda | D84: Emenda ao PL 182/2024 | E84: Sim | F84: 52 a 16 | G84: Aprovado | H84: Não | I84: Sim | J84: contra o governo | K84: 6877
A85: 45608 | B85: PLP 175/2024 | C85: Texto principal | D85: Regras de transparência e execução das emendas parlamentares | E85: Não | F85: 46 a 18 | G85: Aprovado | H85: Sim | I85: Liberou | J85: contra o governo | K85: 6878
A86: 45614 | B86: PLP 175/2024 | C86: Destaque ou emenda | D86: Bloqueio de emendas parlamentares, dispositivo destacado | E86: Não | F86: 14 a 47 | G86: Rejeitado | H86: Sim | I86: Não | J86: contra o governo | K86: 6879
A87: 45614 | B87: PLP 175/2024 | C87: Destaque ou emenda | D87: Dispositivo destacado do projeto das emendas parlamentares | E87: Não | F87: 25 a 39 | G87: Rejeitado | H87: Sim | I87: Não | J87: contra o governo | K87: 6880
... A112: 45727 | B112: PEC 18/2024 | C112: Texto principal | D112: Inclui o Pantanal entre os patrimônios nacionais da Constituição, 2º turno | E112: Não Compareceu | F112: 70 a 0 | G112: Aprovado | H112: Sim | I112: Sim | J112: ausente; PEC: folga sobre os 49 votos = 21 | K112: 6920
A113: 45734 | B113: PLP 192/2023 | C113: Procedimento | D113: Questão de ordem sobre o PLP 192/2023 (Lei de Inelegibilidades) | E113: Sim | F113: 34 a 21 | G113: Rejeitado | H113: Não orientou | I113: Sim | K113: 6921
A114: 45735 | B114: PLP 22/2025 (Substitutivo-CD) | C114: Texto principal | D114: Prazo para liquidação de restos a pagar, texto da Câmara | E114: Sim | F114: 66 a 2 | G114: Aprovado | H114: Sim | I114: Sim | J114: voto com placar folgado | K114: 6922
A115: 45748 | B115: PLP 201/2019 | C115: Texto principal | D115: Participação popular e audiências públicas na elaboração do orçamento | E115: Presente – Não registrou voto | F115: 54 a 2 | G115: Aprovado | H115: Sim | I115: Sim | J115: presente sem votar (votou outros itens no dia) | K115: 6923
A116: 45748 | B116: PL 2088/2023 | C116: Texto principal | D116: Exige de produtos importados padrões ambientais compatíveis com os do Brasil | E116: Sim | F116: 70 a 0 | G116: Aprovado | H116: Sim | I116: Sim | J116: voto com placar folgado | K116: 6924
A117: 45755 | B117: PEC 2/2016 | C117: Texto principal | D117: Inclui o saneamento básico entre os direitos sociais, 1º turno | E117: Sim | F117: 64 a 0 | G117: Aprovado | H117: Sim | I117: Sim | J117: PEC: folga sobre os 49 votos = 15; voto com placar folgado | K117: 6925
A118: 45755 | B118: PEC 2/2016 | C118: Texto principal | D118: Inclui o saneamento básico entre os direitos sociais, 2º turno | E118: Sim | F118: 59 a 0 | G118: Aprovado | H118: Sim | I118: Sim | J118: PEC: folga sobre os 49 votos = 10 | K118: 6926
A119: 45776 | B119: PLP 48/2023 | C119: Texto principal | D119: Flexibiliza uso de recursos transferidos na educação | E119: Sim | F119: 52 a 0 | G119: Aprovado | H119: Sim | I119: Sim | K119: 6927
A120: 45797 | B120: PEC 81/2015 | C120: Texto principal | D120: Competência concorrente para legislar sobre proteção ao idoso, 1º turno | E120: Atividade parlamentar | F120: 57 a 0 | G120: Aprovado | H120: Sim | I120: Sim | J120: ausente; PEC: folga sobre os 49 votos = 8 | K120: 6928
A121: 45797 | B121: PEC 81/2015 | C121: Texto principal | D121: Competência concorrente para legislar sobre proteção ao idoso, 2º turno | E121: Atividade parlamentar | F121: 55 a 0 | G121: Aprovado | H121: Sim | I121: Sim | J121: ausente; PEC: folga sobre os 49 votos = 6 | K121: 6929
A122: 45798 | B122: PL 2159/2021 | C122: Texto principal | D122: Nova lei geral do licenciamento ambiental (PL 2.159/2021) | E122: Sim | F122: 54 a 13 | G122: Aprovado | H122: Liberou | I122: Sim | K122: 6935
A123: 45804 | B123: PEC 37/2022 | C123: Texto principal | D123: Guardas municipais e agentes de trânsito na segurança pública, 1º turno | E123: Licença Particular | F123: 65 a 0 | G123: Aprovado | H123: Sim | I123: Sim | J123: ausente; PEC: folga sobre os 49 votos = 16 | K123: 6936
A124: 45804 | B124: PEC 37/2022 | C124: Destaque ou emenda | D124: Emenda à PEC das guardas municipais | E124: Licença Particular | F124: 16 a 42 | G124: Rejeitado | H124: Não orientou | I124: Liberou | J124: ausente | K124: 6937
A125: 45804 | B125: PEC 37/2022 | C125: Texto principal | D125: Guardas municipais e agentes de trânsito na segurança pública, 2º turno | E125: Licença Particular | F125: 57 a 0 | G125: Aprovado | H125: Sim | I125: Sim | J125: ausente; PEC: folga sobre os 49 votos = 8 | K125: 6938
A126: 45804 | B126: PLP 234/2020 | C126: Texto principal | D126: Compras públicas para fomentar micro e pequenas empresas | E126: Licença Particular | F126: 56 a 0 | G126: Aprovado | H126: Não orientou | I126: Não orientou | J126: ausente | K126: 6939
A127: 45833 | B127: RQS 451/2025 | C127: Procedimento | D127: Urgência para o projeto que aumenta o número de deputados | E127: Não | F127: 43 a 30 | G127: Aprovado | H127: Não orientou | I127: Liberou | K127: 6950
A128: 45833 | B128: PLP 177/2023 | C128: Texto principal | D128: Aumenta o número de deputados federais | E128: Não | F128: 41 a 33 | G128: Aprovado | H128: Não orientou | I128: Não orientou | K128: 6951
A129: 45833 | B129: PLP 177/2023 | C129: Destaque ou emenda | D129: Emenda ao projeto do número de deputados | E129: Sim | F129: 20 a 26 | G129: Rejeitado | H129: Não orientou | I129: Liberou | K129: 6952
A130: 45833 | B130: PLP 177/2023 | C130: Procedimento | D130: Urgência para o projeto que aumenta o número de deputados | E130: Não | F130: 43 a 30 | G130: Aprovado | H130: Não orientou | I130: Liberou | K130: 6953
A131: 45839 | B131: MPV 1291/2025 | C131: Destaque ou emenda | D131: Artigo destacado do PLV 2/2025 (MPV 1.291/2025) | E131: Não | F131: 37 a 17 | G131: Aprovado | H131: Sim | I131: Não | J131: contra o governo | K131: 6954
A132: 45840 | B132: PLP 167/2024 | C132: Texto principal | D132: Programa Acredita Exportação para pequenos negócios | E132: Sim | F132: 52 a 0 | G132: Aprovado | H132: Sim | I132: Sim | K132: 6955
...
